
{
    "notice": "[SMR]20260609 🐒",,
   "wallpaper":"https://深色壁纸.xxooo.cf/",
   "sites":[
      






{
            "key": "✨高清福利社✨",
            "name": "🏆✨高清福利社✨",
            "type": 3,
            "playerType": 2,
            "api": "csp_XBPQ",
            "jar": "https://github.com/franksun1211/TXT/raw/main/HTB/PG/jar/xyqxbpq.jar",
            "searchable": 1,
            "quickSearch": 1,
            "filterable": 1,
            "ext": "https://github.com/franksun1211/TXT/raw/main/HTB/PG/json/高清福利社.json"
        },

 {
      "key": "麻豆",
      "name": "✨成人專區✨",
      "type": 3,
      "changeable": 1,
      "filterable": 1,
      "api": "csp_XBPQ",
      "jar": "https://github.com/franksun1211/TXT/raw/main/TVbox/E8jin/lib/xyqxbpq.jar",
      "style": {
        "ratio": 1.7
      },
      "ext": {
        "分类url": "http://gcmd.cc/index.php/vod/show/class/{class}/id/{cateId}/page/{catePg}.html",
        "搜索url": "http://gcmd.cc/index.php/vod/search/page/{pg}/wd/{wd}.html",
        "分类": "麻豆视频$1#日本视频$2#國產視頻$3",
        "剧情": "大乳房&体内射精&水手服&紧身衣&单一作品&荡妇&脏话&女同性恋&业余&角色扮演&和服&女教师&连裤袜||麻豆&天美&蜜桃&皇家&精东&星空&萝莉社&糖心Vlog&乐播&兔子先生&杏吧&果冻&PsychoPorn||萝莉&大奶&交内射&吞精&勾搭&骚穴&车震&约炮&骚货&母狗&捆绑&调教",
        "直接播放": "1"
      }
    },

{"key": "Supjav",
    "name": "🔞Supjav",
    "type": 3,
    "api": "csp_Supjav",
    "jar":"https://od.lk/s/NjFfMTI2MzM0NTE4Xw/xc0126.png",
    "searchable": 1,
    "quickSearch": 1,
    "filterable": 1,
    "style": {
        "type": "rect",
        "ratio": 1.777
    }
},
{
            "key": "csp_XYQHiker_黄色仓库123",
            "name": "🔞黄色仓库",
            "type": 3,
            "api": "csp_XYQHiker",
            "jar": "https://od.lk/s/NjFfMTI2ODU2MjY2Xw/hsck.png",
            "searchable": 1,
            "quickSearch": 0,
            "filterable": 0,
            "ext": "https://ghfast.top/https://raw.githubusercontent.com/xwyjc/lwang/main/XYQHike/黄色仓库123.json",
            "style": {
                "type": "rect",
                "ratio": 1.6
            }
        },






{
            "key": "禁片天堂.py",
            "name": "🈲🔞禁片天堂.py",
            "type": 3,
            "searchable": 1,
            "quickSearch": 1,
            "filterable": 1,
            "api": "https://github.com/franksun1211/TXT/raw/main/TVbox/SMR/PY/kptt.py",
            "order_num": 5,
            "ext": ""
        }, 



{
            "key": "javxx",
            "name": "🔞 JAVXX",
            "type": 3,
            "searchable": 1,
            "quickSearch": 0,
            "filterable": 0,
            "api": "https://github.com/franksun1211/TXT/raw/main/TVbox/SMR/PY/javxx.py",
            "ext": {
                "proxy": {},
                "plp": ""
            }
        },






{"key": "jable","name": "🔞 jable", "type": 3,"changeable": 1, "searchable": 1,"quickSearch": 1, "filterable": 1,"api": "csp_XBPQ", 
"jar": "https://files.catbox.moe/6ffxsq.png",
"ext":{"直接播放":"1", "搜索模式":"1", "搜索url":"https://jable.tv/search/{wd}/", "数组":"<div class=\"img-box cover-md\">&&</h6>", "图片":"data-src=\"&&\"", "标题":"class=\"title\">&&</a>", "链接":"href=\"&&\"", "链接前缀":"https://jable.tv", "副标题":"<span class=\"label\">&&</span>", "播放数组":"<h6&&</h6>", "播放列表":"<a&&/a>", "播放标题":">&&<", "播放链接":"href=\"&&\"", "分类":"最近更新$latest-updates#最新上市$new-release#主奴调教$categories/bdsm#字幕$categories/chinese-subtitle#凌辱$categories/rape#制服$categories/uniform#角色$categories/roleplay#偷拍$categories/hidden-cam#无码解码$categories/uncensored#多P$categories/groupsex#丝袜$categories/pantyhose", "分类url":"https://jable.tv/{cateId}/{catePg}/", "免嗅":"0", "嗅探词":".m3u8#.mp4", "页面代理":"127.0.0.1:10072"}}, 






        
        {
            "key": "JAVDAY",
            "name": "🔞JAVDAY",
            "type": 3,
            "api": "csp_XYQHiker",
            "jar": "https://files.catbox.moe/6ffxsq.png",
            "searchable": 1,
            "quickSearch": 0,
            "filterable": 0,
            "ext": "https://ghfast.top/https://raw.githubusercontent.com/xwyjc/lwang/main/XYQHike/javday.json",
            "style": {
                "type": "rect",
                "ratio": 1.6
            }
        },
        
        
        
     







        {
            "key": "csp_XYQHiker_xnxx",
            "name": "🔞XNXX",
            "type": 3,
            "api": "csp_XYQHiker",
            "jar": "https://files.catbox.moe/6ffxsq.png",
            "searchable": 1,
            "quickSearch": 0,
            "filterable": 0,
            "ext": "https://ghfast.top/https://raw.githubusercontent.com/xwyjc/lwang/main/XYQHike/xnxx.json",
            "style": {
                "type": "rect",
                "ratio": 1.6
            }
        },
        
        
        
        {
            "key": "csp_XYQHiker_njavtv.com",
            "name": "🔞Njavtv",
            "type": 3,
            "api": "csp_XYQHiker",
            "jar": "https://files.catbox.moe/6ffxsq.png",
            "searchable": 1,
            "quickSearch": 0,
            "filterable": 0,
            "ext": "https://ghfast.top/https://raw.githubusercontent.com/xwyjc/lwang/main/XYQHike/njavtv.json",
            "style": {
                "type": "rect",
                "ratio": 1.6
            }
        },
        
        
        
  
        {
            "key": "csp_XYQHiker_18av",
            "name": "🔞18AV",
            "type": 3,
            "api": "csp_XYQHiker",
            "jar": "https://files.catbox.moe/6ffxsq.png",
            "searchable": 1,
            "quickSearch": 0,
            "filterable": 0,
            "ext": "https://ghfast.top/https://raw.githubusercontent.com/xwyjc/lwang/main/XYQHike/18av.json",
            "style": {
                "type": "rect",
                "ratio": 1.6
            }
        },

        
        
        
        {
            "key": "csp_XYQHiker_javffm",
            "name": "🔞JAVFFM",
            "type": 3,
            "api": "csp_XYQHiker",
            "jar": "https://files.catbox.moe/6ffxsq.png",
            "searchable": 1,
            "quickSearch": 0,
            "filterable": 0,
            "ext": "https://ghfast.top/https://raw.githubusercontent.com/xwyjc/lwang/main/XYQHike/javffm.json",
            "style": {
                "type": "rect",
                "ratio": 1.6
            }
        },
        
        
        
        
        
        {
            "key": "csp_XYQHiker_javtsunami",
            "name": "🔞javtsunami",
            "type": 3,
            "api": "csp_XYQHiker",
            "jar": "https://files.catbox.moe/6ffxsq.png",
            "searchable": 1,
            "quickSearch": 0,
            "filterable": 0,
            "ext": "https://ghfast.top/https://raw.githubusercontent.com/xwyjc/lwang/main/XYQHike/javtsunami.json",
            "style": {
                "type": "rect",
                "ratio": 1.6
            }
        },
        
              
        
        
        




{
            "key": "hhh",
            "name": "🔞truvaze",
            "type": 3,
            "searchable": 1,
            "quickSearch": 1,
            "filterable": 1,
            "api": "https://github.com/franksun1211/TXT/raw/main/TVbox/SMR/PY/truvazex.py",
            "order_num": 5,
            "ext": ""
        },




        
{
            "key": "av.py",
            "name": "🔞av.py",
            "type": 3,
            "searchable": 1,
            "quickSearch": 1,
            "filterable": 1,
            "api": "https://github.com/franksun1211/TXT/raw/main/TVbox/SMR/PY/av.py",
            "order_num": 5,
            "ext": ""
        },




        

{
            "key": "JAV36",
            "name": "🔞JAV36",
            "type": 3,
            "searchable": 1,
            "quickSearch": 1,
            "filterable": 1,
            "api": "https://github.com/franksun1211/TXT/raw/main/TVbox/SMR/PY/JAV36.py",
            "order_num": 5,
            "ext": ""
        },




        
{
            "key": "pigav",
            "name": "🔞PigAV",
            "type": 3,
            "searchable": 1,
            "quickSearch": 1,
            "filterable": 1,
            "api": "https://github.com/franksun1211/TXT/raw/main/TVbox/SMR/PY/PigAV.py",
            "order_num": 5,
            "ext": ""
        },




        


{
            "key": "H",
            "name": "🔞V-HUB",
            "type": 3,
            "searchable": 1,
            "quickSearch": 1,
            "filterable": 1,
            "api": "https://github.com/franksun1211/TXT/raw/main/TVbox/SMR/PY/V-HUB.py",
            "order_num": 5,
            "ext": ""
        },




        {
            "key": "蘿莉AV.py",
            "name": "🔞蘿莉AV.py",
            "type": 3,
            "searchable": 1,
            "quickSearch": 1,
            "filterable": 1,
            "api": "https://github.com/franksun1211/TXT/raw/main/TVbox/SMR/PY/蘿莉AV.py",
            "order_num": 5,
            "ext": ""
        },




{
            "key": "愛豆AV.py",
            "name": "🔞愛豆AV.py",
            "type": 3,
            "searchable": 1,
            "quickSearch": 1,
            "filterable": 1,
            "api": "https://github.com/franksun1211/TXT/raw/main/TVbox/SMR/PY/愛豆AV.py",
            "order_num": 5,
            "ext": ""
        },





{
            "key": "性愛大師.py",
            "name": "🔞性愛大師.py",
            "type": 3,
            "searchable": 1,
            "quickSearch": 1,
            "filterable": 1,
            "api": "https://github.com/franksun1211/TXT/raw/main/TVbox/SMR/PY/性愛大師.py",
            "order_num": 5,
            "ext": ""
        },







{
            "key": "Twojav.py",
            "name": "🔞Twojav.py",
            "type": 3,
            "searchable": 1,
            "quickSearch": 1,
            "filterable": 1,
            "api": "https://github.com/franksun1211/TXT/raw/main/TVbox/SMR/PY/Twojav.py",
            "order_num": 5,
            "ext": ""
        },



{
            "key": "高清仓库.py",
            "name": "🔞高清仓库.py",
            "type": 3,
            "searchable": 1,
            "quickSearch": 1,
            "filterable": 1,
            "api": "https://github.com/franksun1211/TXT/raw/main/TVbox/SMR/PY/高清仓库.py",
            "order_num": 5,
            "ext": ""
        },




{
            "key": "久久視頻.py",
            "name": "🔞久久視頻.py",
            "type": 3,
            "searchable": 1,
            "quickSearch": 1,
            "filterable": 1,
            "api": "https://github.com/franksun1211/TXT/raw/main/TVbox/SMR/PY/久久視頻.py",
            "order_num": 5,
            "ext": ""
        },







        {
            "key": "AVBeBe.py",
            "name": "🔞AVBeBe.py",
            "type": 3,
            "searchable": 1,
            "quickSearch": 1,
            "filterable": 1,
            "api": "https://github.com/franksun1211/TXT/raw/main/TVbox/SMR/PY/AVBeBe.py",
            "order_num": 5,
            "ext": ""
        },




        





{"key": "17av.app","name": "🔞蜜桃",
      "type": 3,"api": "csp_XBPQ",
      "searchable": 1,"quickSearch": 1,"filterable": 1,
      "jar": "https://files.catbox.moe/rlgljm.png;md5;5263cb4e5f6d2ca968940edc6e935faf",
      "ext": { 
       "数组":"<div class=\"col-style d-4 m-2 lazy loaded\">&&</div></a></div>",
       "图片":"src=\"&&\"",
       "链接": "href=\"&&\"",
       "标题": "title=\"&&\"",
	    "简介":"小撸怡情，大撸伤身！！",
	    "副标题": "<span class=\"number\">&&</span>",
		"线路数组":">线路：&&<section class=\"sectionContent below_path_content\">",
		"线路标题": ">福利线路<",
	   "播放数组":">线路：&&<section class=\"sectionContent below_path_content\">",
	   "播放列表": "<a&&a>",
	   "播放标题": ">&&</",
	   "播放链接": "href=\"&&\"",
	    "搜索模式":"1",
        "搜索url":"https://www.17av.app/vodsearch/{wd}/page/{pg}.html",
	   "搜索链接前缀":"https://www.17av.app/vodplay/",
       "搜索链接后缀":"-1-1.html",
       "分类url": "https://www.17av.app/vodtype/{cateId}-{catePg}.html",
	    "分类数组": "<a&&a>",
       "分类标题": ">&&</",
        "分类ID": "/vodtype/&&.html"}},
	  
	  
	  




	
	{"key": "花都影视发布页地址：a.hdys.top a.hdys.xyz","name": "🔞花都",
	"type": 3,"api": "csp_XBPQ","filterable": 1,
	"jar": "https://files.catbox.moe/rlgljm.png;md5;5263cb4e5f6d2ca968940edc6e935faf",
	"ext": { "主页url": "https://huaduys.com/", 
	 "数组":"stui-vodlist__box\">&&</div></div>",
	 "图片": "data-original=\"&&\"",
     "标题":"title=\"&&\"",
	"简介": "description\" content=\"&&剧情",  
	"链接": "/vodplay/+href=\"/voddetail/&&.html\"+-1-1.html",
    "直接播放":"1",
	"分类":"中字骑兵$6#日本骑兵$7#中字步兵$8#日本步兵$9#国产传媒$11#糖心vlog$13#国产精品$10", 
	"搜索模式": "1", 
	"搜索url": "https://huaduys.com/vodsearch/-------------.html?wd={wd}",
	"分类url":"https://huaduys.com/vodshow/{cateId}--{by}------{catePg}---.html"
	}},
	
	
	  
	
 
	






{
      "key": "kk",
      "name": "🔞❶",
      "type": 1,
      "api": "https://155api.com/api.php/provide/vod/?ac=list",
      "searchable": 1,
      "quickSearch": 1,
      "filterable": 1
    },
   
   
   
   
    {
      "key": "xx",
      "name": "🔞❷",
      "type": 0,
      "api": "https://xingba222.com/api.php/provide/vod/at/xml",
      "searchable": 1,
      "quickSearch": 1,
      "filterable": 1
    }, 







{
         "key":"🈲🔞大地X资源站",
         "name":"🈲🔞大地X资源站",
         "type":0,
         "api":"https://dadiapi.com/api.php/provide/vod/",
         "searchable":1,
         "filterable":0,
         "changeable":1
    },







{
      "key": "alvin",
      "name": "🔞Alvin
",
      "type": 0,
      "api": "http://lbapiby.com/api.php/provide/vod/at/xml"
    },


{
            "key": "番外",
            "name": "🔞番外采集",
            "type": 1,
            "api": "http://fhapi9.com/api.php/provide/vod/",
            "playUrl": "",
            "searchable": 1,
            "quickSearch": 0,
            "filterable": 1,
            "categories": [
                "群交淫乱",
                "偷拍自拍",
                "制服丝袜",
                "无码专区",
                "卡通动漫",
                "中文字幕",
                "欧美性爱",
                "巨乳美乳",
                "国产裸聊",
                "国产自拍",
                "国产盗摄",
                "伦理三级",
                "女同性恋",
                "少女萝莉",
                "人妖系列",
                "虚拟VR"
            ]
        },
        
{
      "key": "9号资源",
      "name": "🔞9号资源",
      "type": 0,
      "api": "http://fhapi9.com/api.php/provide/vod/at/xml/",
      "searchable": 1,
      "quickSearch": 1,
      "filterable": 0
    }





   ],
   "lives":[


       {
            "name": "🔞 CR",
            "type": 0,
            "url": "https://od.lk/s/NjFfMTI2ODY2NDU0Xw/CR.txt",
            "playerType": 2,
            "epg": "http://epg.112114.xyz/?ch={name}&date={date}&serverTimeZone=Asia%2FHong_Kong",
            "logo": "https://epg.112114.xyz/logo/{name}.png"
        },


        
   
  

{
      "name": "🌈 mytvsuper (Yang) 🌈",
      "type": 0,
      "ua": "okhttp/5.0.0-alpha.14",
      "url": "https://iptv.yang-1989.eu.org/m3u/myTV.m3u",
      "playerType": 1
    },



{
            "name": "✨ JACK TV",
            "type": 0,
            "url": "https://php.946985.filegear-sg.me/jackTV.m3u",
            "playerType": 2,
            "epg": "http://epg.112114.xyz/?ch={name}&date={date}&serverTimeZone=Asia%2FHong_Kong",
            "logo": "https://epg.112114.xyz/logo/{name}.png"
        },



{
            "name": "♒ TV123",
            "type": 0,
            "url": "http://tv123.vvvv.ee/tv.m3u",
            "playerType": 2,
            "epg": "http://epg.112114.xyz/?ch={name}&date={date}&serverTimeZone=Asia%2FHong_Kong",
            "logo": "https://epg.112114.xyz/logo/{name}.png"
        }, 





{
            "name": "♎ 风云TV",
            "type": 0,
            "url": "http://iptv.4666888.xyz/FYTV.txt",
            "playerType": 2,
            "epg": "http://epg.112114.xyz/?ch={name}&date={date}&serverTimeZone=Asia%2FHong_Kong",
            "logo": "https://epg.112114.xyz/logo/{name}.png"
        }, 





{
            "name": "🌠 宫殿TV",
            "type": 0,
            "url": "https://gongdian.top/tv/iptv",
            "playerType": 2,
            "epg": "http://epg.112114.xyz/?ch={name}&date={date}&serverTimeZone=Asia%2FHong_Kong",
            "logo": "https://epg.112114.xyz/logo/{name}.png"
        }, 




{
            "name": "♎ 易发TV",
            "type": 0,
            "url": "https://gh-proxy.org/https://raw.githubusercontent.com/fafa002/yf2025/refs/heads/main/yiyifafa.txt",
            "playerType": 2,
            "epg": "http://epg.112114.xyz/?ch={name}&date={date}&serverTimeZone=Asia%2FHong_Kong",
            "logo": "https://epg.112114.xyz/logo/{name}.png"
        }


   
   
   
   ],
   "doh":[
      {
         "name":"Google",
         "url":"https://dns.google/dns-query",
         "ips":[
            "8.8.4.4",
            "8.8.8.8"
         ]
      },
      {
         "name":"Cloudflare",
         "url":"https://cloudflare-dns.com/dns-query",
         "ips":[
            "1.1.1.1",
            "1.0.0.1",
            "2606:4700:4700::1111",
            "2606:4700:4700::1001"
         ]
      },
      {
         "name":"AdGuard",
         "url":"https://dns.adguard.com/dns-query",
         "ips":[
            "94.140.14.140",
            "94.140.14.141"
         ]
      },
      {
         "name":"DNSWatch",
         "url":"https://resolver2.dns.watch/dns-query",
         "ips":[
            "84.200.69.80",
            "84.200.70.40"
         ]
      },
      {
         "name":"Quad9",
         "url":"https://dns.quad9.net/dns-quer",
         "ips":[
            "9.9.9.9",
            "149.112.112.112"
         ]
      }
   ]
}



























